sovtimer/__init__.py
sovtimer/app_settings.py
sovtimer/apps.py
sovtimer/auth_hooks.py
sovtimer/constants.py
sovtimer/models.py
sovtimer/providers.py
sovtimer/tasks.py
sovtimer/urls.py
sovtimer/views.py
sovtimer/handler/esi_handler.py
sovtimer/locale/.gitkeep
sovtimer/locale/django.pot
sovtimer/locale/cs_CZ/LC_MESSAGES/django.mo
sovtimer/locale/cs_CZ/LC_MESSAGES/django.po
sovtimer/locale/de/LC_MESSAGES/django.mo
sovtimer/locale/de/LC_MESSAGES/django.po
sovtimer/locale/es/LC_MESSAGES/django.mo
sovtimer/locale/es/LC_MESSAGES/django.po
sovtimer/locale/fr_FR/LC_MESSAGES/django.mo
sovtimer/locale/fr_FR/LC_MESSAGES/django.po
sovtimer/locale/it_IT/LC_MESSAGES/django.mo
sovtimer/locale/it_IT/LC_MESSAGES/django.po
sovtimer/locale/ja/LC_MESSAGES/django.mo
sovtimer/locale/ja/LC_MESSAGES/django.po
sovtimer/locale/ko_KR/LC_MESSAGES/django.mo
sovtimer/locale/ko_KR/LC_MESSAGES/django.po
sovtimer/locale/nl_NL/LC_MESSAGES/django.mo
sovtimer/locale/nl_NL/LC_MESSAGES/django.po
sovtimer/locale/pl_PL/LC_MESSAGES/django.mo
sovtimer/locale/pl_PL/LC_MESSAGES/django.po
sovtimer/locale/ru/LC_MESSAGES/django.mo
sovtimer/locale/ru/LC_MESSAGES/django.po
sovtimer/locale/sk/LC_MESSAGES/django.mo
sovtimer/locale/sk/LC_MESSAGES/django.po
sovtimer/locale/uk/LC_MESSAGES/django.mo
sovtimer/locale/uk/LC_MESSAGES/django.po
sovtimer/locale/zh_Hans/LC_MESSAGES/django.mo
sovtimer/locale/zh_Hans/LC_MESSAGES/django.po
sovtimer/management/commands/__init__.py
sovtimer/management/commands/sovtimer_load_initial_data.py
sovtimer/migrations/0001_initial.py
sovtimer/migrations/0002_aasovtimercampaigns_aasovtimerstructures.py
sovtimer/migrations/0003_auto_20201113_1033.py
sovtimer/migrations/0004_auto_20201113_1856.py
sovtimer/migrations/0005_auto_20201114_0720.py
sovtimer/migrations/0006_rename_models.py
sovtimer/migrations/0007_cleanup_models.py
sovtimer/migrations/0008_fix_campaign_attackers_score.py
sovtimer/migrations/0009_alter_campaign_options_and_more.py
sovtimer/migrations/0010_alter_campaign_event_type.py
aa_sov_timer-3.3.2.dist-info/METADATA
aa_sov_timer-3.3.2.dist-info/WHEEL
aa_sov_timer-3.3.2.dist-info/licenses/LICENSE
aa_sov_timer-3.3.2.dist-info/RECORD
